localkin_service_audio/README.md
localkin_service_audio/__init__.py
localkin_service_audio/api/__init__.py
localkin_service_audio/api/server.py
localkin_service_audio/cli/__init__.py
localkin_service_audio/cli/cli.py
localkin_service_audio/core/__init__.py
localkin_service_audio/core/config.py
localkin_service_audio/core/models.json
localkin_service_audio/core/models.py
localkin_service_audio/core/audio_processing/__init__.py
localkin_service_audio/core/audio_processing/stt.py
localkin_service_audio/core/audio_processing/tts.py
localkin_service_audio/core/audio_processing/whisper_cpp.py
localkin_service_audio/samples/sample.wav
localkin_service_audio/templates/__init__.py
localkin_service_audio/templates/model_templates.py
localkin_service_audio/ui/__init__.py
localkin_service_audio/ui/routes.py
localkin_service_audio/ui/static/publish_to_pypi.sh
localkin_service_audio/ui/templates/base.html
localkin_service_audio/ui/templates/index.html
localkin_service_audio/ui/templates/synthesize.html
localkin_service_audio/ui/templates/transcribe.html
localkin_service_audio/utils/__init__.py
localkin_service_audio/utils/generate_audio.py
localkin_service_audio-1.1.3.dist-info/licenses/LICENSE
localkin_service_audio-1.1.3.dist-info/METADATA
localkin_service_audio-1.1.3.dist-info/WHEEL
localkin_service_audio-1.1.3.dist-info/entry_points.txt
localkin_service_audio-1.1.3.dist-info/top_level.txt
localkin_service_audio-1.1.3.dist-info/RECORD
