Metadata-Version: 2.4
Name: localkin-service-audio
Version: 1.1.3
Summary: Local Speech-to-Text and Text-to-Speech Model Manager
Author-email: LocalKin Team <info@localkin.dev>
Maintainer-email: LocalKin Team <info@localkin.dev>
License-Expression: MIT
Project-URL: Homepage, https://localkin.ai/
Project-URL: Documentation, https://localkin.ai/
Project-URL: Repository, https://github.com/LocalKinAI/localkin-service-audio
Project-URL: Issues, https://github.com/LocalKinAI/localkin-service-audio/issues
Project-URL: Changelog, https://github.com/LocalKinAI/localkin-service-audio/blob/main/CHANGELOG.md
Keywords: speech-to-text,text-to-speech,stt,tts,whisper,ollama,local-ai,audio-processing,machine-learning,ai
Classifier: Development Status :: 3 - Alpha
Classifier: Intended Audience :: Developers
Classifier: Intended Audience :: End Users/Desktop
Classifier: Operating System :: OS Independent
Classifier: Programming Language :: Python :: 3
Classifier: Programming Language :: Python :: 3.10
Classifier: Programming Language :: Python :: 3.11
Classifier: Programming Language :: Python :: 3.12
Classifier: Topic :: Multimedia :: Sound/Audio :: Speech
Classifier: Topic :: Scientific/Engineering :: Artificial Intelligence
Classifier: Topic :: Utilities
Requires-Python: >=3.10
License-File: LICENSE
Requires-Dist: requests>=2.25.0
Requires-Dist: sounddevice>=0.4.0
Requires-Dist: scipy>=1.7.0
Requires-Dist: numpy<1.25.0,>=1.21.0
Requires-Dist: openai-whisper==20240930
Requires-Dist: faster-whisper>=1.0.0
Requires-Dist: pyttsx3>=2.90
Requires-Dist: huggingface-hub>=0.17.0
Requires-Dist: transformers>=4.21.0
Requires-Dist: torch>=2.0.0
Requires-Dist: torchaudio>=2.0.0
Requires-Dist: kokoro>=0.9.2
Requires-Dist: soundfile>=0.12.0
Requires-Dist: fastapi>=0.104.0
Requires-Dist: uvicorn>=0.24.0
Requires-Dist: pydantic>=2.0.0
Requires-Dist: python-multipart>=0.0.6
Requires-Dist: llvmlite>=0.41.0
Requires-Dist: numba>=0.58.0
Requires-Dist: ctranslate2>=4.0.0
Requires-Dist: sentencepiece>=0.2.1
Requires-Dist: TTS>=0.22.0
Requires-Dist: pywhispercpp>=1.0.0
Requires-Dist: librosa>=0.10.0
Provides-Extra: dev
Requires-Dist: pytest>=6.0.0; extra == "dev"
Requires-Dist: black>=21.0.0; extra == "dev"
Requires-Dist: flake8>=3.9.0; extra == "dev"
Requires-Dist: mypy>=0.900; extra == "dev"
Requires-Dist: pre-commit>=2.15.0; extra == "dev"
Requires-Dist: ruff>=0.1.0; extra == "dev"
Provides-Extra: docs
Requires-Dist: sphinx>=4.0.0; extra == "docs"
Requires-Dist: sphinx-rtd-theme>=1.0.0; extra == "docs"
Requires-Dist: myst-parser>=0.15.0; extra == "docs"
Provides-Extra: web
Requires-Dist: jinja2>=3.0.0; extra == "web"
Requires-Dist: python-multipart>=0.0.6; extra == "web"
Provides-Extra: tts
Requires-Dist: TTS>=0.22.0; extra == "tts"
Provides-Extra: gpu
Requires-Dist: torch>=2.0.0; extra == "gpu"
Requires-Dist: torchaudio>=2.0.0; extra == "gpu"
Dynamic: license-file
